virxrlcu.cp39-win_amd64.pyd
VirxERLU_CLib-2.0.9.dist-info/METADATA
VirxERLU_CLib-2.0.9.dist-info/WHEEL
VirxERLU_CLib-2.0.9.dist-info/top_level.txt
VirxERLU_CLib-2.0.9.dist-info/RECORD
