Metadata-Version: 2.1
Name: VirxERLU-CLib
Version: 2.0.9
Summary: C modules for VirxERLU
Home-page: https://github.com/VirxEC/VirxERLU-CLib
Author: VirxEC
Author-email: virx@virxcase.dev
License: MIT
Platform: UNKNOWN
Requires-Python: >=3.7
